xchk_git_content/__init__.py
xchk_git_content/apps.py
xchk_git_content/contentviews.py
xchk_git_content/course.py
xchk_git_content/static/xchk_git_content/images/add-file-bitbucket-web-interface.png
xchk_git_content/static/xchk_git_content/images/bitbucket-new-repo.png
xchk_git_content/static/xchk_git_content/images/bitbucket-remote-via-https.png
xchk_git_content/static/xchk_git_content/images/git-stages-basics.png
xchk_git_content/static/xchk_git_content/images/officieel-boek-git.png
xchk_git_content/static/xchk_git_content/images/output-git-log.png
xchk_git_content/static/xchk_git_content/images/remotes-example.png
xchk_git_content/static/xchk_git_content/images/remotes-quiz.png
xchk_git_content/strats.py
xchk_git_content/templates/xchk_git_content/git_add_remote.html
xchk_git_content/templates/xchk_git_content/git_basics_self_test.html
xchk_git_content/templates/xchk_git_content/git_log.html
xchk_git_content/templates/xchk_git_content/git_pull.html
xchk_git_content/templates/xchk_git_content/git_push.html
xchk_git_content/templates/xchk_git_content/git_remotes_concept.html
xchk_git_content/templates/xchk_git_content/git_rm.html
xchk_git_content/templates/xchk_git_content/git_stage_changes.html
xchk_git_content/templates/xchk_git_content/git_stages.html
xchk_git_content/templates/xchk_git_content/git_status.html
xchk_git_content/templates/xchk_git_content/git_status_and_gitignore.html
xchk_git_content/templates/xchk_git_content/gitignore_concept.html
xchk_git_content/templates/xchk_git_content/start_git_init.html
xchk_git_content/templates/xchk_git_content/what_is_git.html
xchk_git_content/tests.py
xchk_git_content/urls.py
xchk_git_content/views.py
xchk_git_content-0.1.11.dist-info/WHEEL
xchk_git_content-0.1.11.dist-info/METADATA
xchk_git_content-0.1.11.dist-info/RECORD
